CONTRIBUTORS.rst
MANIFEST.in
Makefile
README.rst
setup.py
konfig/__init__.py
konfig.egg-info/PKG-INFO
konfig.egg-info/SOURCES.txt
konfig.egg-info/dependency_links.txt
konfig.egg-info/not-zip-safe
konfig.egg-info/requires.txt
konfig.egg-info/top_level.txt
konfig/tests/__init__.py
konfig/tests/test_config.py