Metadata-Version: 1.0
Name: konfig
Version: 0.8
Summary: Yet Another Config Parser.
Home-page: https://github.com/mozilla-services/konfig
Author: Tarek Ziade
Author-email: tarek@mozilla.com
License: UNKNOWN
Platform: UNKNOWN
Classifier: Programming Language :: Python
Classifier: License :: OSI Approved :: Mozilla Public License 2.0 (MPL 2.0)
Classifier: Development Status :: 5 - Production/Stable
